androdf/LICENSE
androdf/README.MD
androdf/__init__.py
androdf/requirements.txt
androdf/thirdparty.json
androdf-0.12.dist-info/LICENSE.rst
androdf-0.12.dist-info/METADATA
androdf-0.12.dist-info/WHEEL
androdf-0.12.dist-info/top_level.txt
androdf-0.12.dist-info/RECORD
