Metadata-Version: 2.1
Name: androdf
Version: 0.12
Summary: Locates more items/views/elements on an Android device than similar automation packages by combining ADB's dumpsys activity/uiautomator
Home-page: https://github.com/hansalemaos/androdf
Author: Johannes Fischer
Author-email: <aulasparticularesdealemaosp@gmail.com>
License: MIT
Keywords: uiautomator,dumpsys,adb,android,debugging,pandas,DataFrame,AndroidManifest,views,items,automation
Classifier: Development Status :: 4 - Beta
Classifier: Programming Language :: Python :: 3 :: Only
Classifier: Programming Language :: Python :: 3.9
Classifier: Topic :: Scientific/Engineering :: Visualization
Classifier: Topic :: Software Development :: Libraries :: Python Modules
Classifier: Topic :: Text Editors :: Text Processing
Classifier: Topic :: Text Processing :: General
Classifier: Topic :: Text Processing :: Indexing
Classifier: Topic :: Text Processing :: Filters
Classifier: Topic :: Utilities
License-File: LICENSE.rst
